MANIFEST.in
README.rst
setup.cfg
setup.py
wordpad/__init__.py
wordpad.egg-info/PKG-INFO
wordpad.egg-info/SOURCES.txt
wordpad.egg-info/dependency_links.txt
wordpad.egg-info/top_level.txt