Metadata-Version: 1.1
Name: wordpad
Version: 0.1.0
Summary: Adds padding to the right or left of a given string
Home-page: https://github.com/scisco/wordpad
Author: Alireza J (scisco)
Author-email: scisco7@gmail.com
License: CC0
Download-URL: https://github.com/scisco/wordpad/tarball/0.1.0
Platform: UNKNOWN
Classifier: Intended Audience :: Developers
Classifier: License :: Freeware
Classifier: Programming Language :: Python :: 2.7
Classifier: Programming Language :: Python :: 3.4
Classifier: Programming Language :: Python :: 3.5
